setup.cfg
setup.py
cloudacademy/__init__.py
cloudacademy/cloudacademy_dl.py
cloudacademy_dl.egg-info/PKG-INFO
cloudacademy_dl.egg-info/SOURCES.txt
cloudacademy_dl.egg-info/dependency_links.txt
cloudacademy_dl.egg-info/entry_points.txt
cloudacademy_dl.egg-info/requires.txt
cloudacademy_dl.egg-info/top_level.txt