Metadata-Version: 1.1
Name: cloudacademy-dl
Version: 0.1.1
Summary: A utility for downloading CloudAcademy.com lecture videos.
Home-page: https://github.com/josefeg/cloudacademy-dl
Author: Josef Galea
Author-email: josefeg@gmail.com
License: MIT
Keywords: cloudacademy-dl,cloudacademy,download,education,MOOCs,video
Platform: any
Classifier: Development Status :: 4 - Beta
Classifier: Environment :: Console
Classifier: Intended Audience :: End Users/Desktop
Classifier: License :: OSI Approved :: MIT License
Classifier: Operating System :: OS Independent
Classifier: Programming Language :: Python :: 3
Classifier: Programming Language :: Python :: 3.3
Classifier: Programming Language :: Python :: 3.4
Classifier: Programming Language :: Python :: 3.5
Classifier: Programming Language :: Python :: Implementation :: CPython
Classifier: Programming Language :: Python :: Implementation :: PyPy
Classifier: Programming Language :: Python
Classifier: Topic :: Education
